{
    "name": "S05977M19__PHA BLA MA DRAN DUS GLU LEN MA_A Song that Came to Me when I Recalled my Lama, my Dear Father_PAn CHEN BLO BZANG CHOS KYI RGYAL MTSAN (1565-1662).TXT",
    "path": "nyams len_personal practice/gsol 'debs_prayers of supplication/pan chen blo bzang chos kyi rgyal mtsan_panchen lobsang chukyi gyeltsen (1565-1662)",
    "download_path": "/sungbum updated 4 26 23 bk/nyams len_personal practice/gsol 'debs_prayers of supplication/pan chen blo bzang chos kyi rgyal mtsan_panchen lobsang chukyi gyeltsen (1565-1662)/s05977m19__pha bla ma dran dus glu len ma_a song that came to me when i recalled my lama, my dear father_pan chen blo bzang chos kyi rgyal mtsan (1565-1662).txt",
    "file_id": "id:Ct2f7NF5r8EAAAAAAAABhw",
    "revision_id": "613f663b87cd08d294473",
    "content_hash": "1643706ca0542149be3110f0b93094eeea38499a507eaa8040febc5b2fc6afc8",
    "server_modified": "2024-03-18T21:53:36",
    "last_sync": "2024-08-26T17:47:25.711809",
    "size": 1915,
    "meta_text": "G CHOS KYI RGYAL MTSAN (1565-1662)",
    "cat_ref": "S05977M19",
    "work_ref": "W.S05977M19",
    "title_tib": "PHA BLA MA DRAN DUS GLU LEN MA",
    "title_eng": "A Song that Came to Me when I Recalled my Lama, my Dear Father",
    "source": "Asian Classics Input Project",
    "collection": "Sungbum",
    "language": "bo",
    "author_simple": "",
    "subject": [
        {
            "_id": "436918503131",
            "subject_path": "NYAMS LEN_PERSONAL PRACTICE/GSOL 'DEBS_PRAYERS OF SUPPLICATION/PAN CHEN BLO BZANG CHOS KYI RGYAL MTSAN_PANCHEN LOBSANG CHUKYI GYELTSEN (1565-1662)",
            "subject_path_tibetan": "NYAMS LEN/GSOL 'DEBS/PAN CHEN BLO BZANG CHOS KYI RGYAL MTSAN",
            "subject_path_english": "PERSONAL PRACTICE/PRAYERS OF SUPPLICATION/PANCHEN LOBSANG CHUKYI GYELTSEN (1565-1662)",
            "subject_tibetan": "PAN CHEN BLO BZANG CHOS KYI RGYAL MTSAN",
            "subject_english": "PANCHEN LOBSANG CHUKYI GYELTSEN (1565-1662)"
        }
    ],
    "items": [],
    "null": "G CHOS KYI RGYAL MTSAN (1565-1662)",
    "author": [
        {
            "author_name": "",
            "author_birth": null,
            "author_death": null
        }
    ],
    "updated": true,
    "path_history": [
        {
            "path": "nyams len_personal practice/gsol 'debs_prayers of supplication/pan chen blo bzang chos kyi rgyal mtsan_panchen lobsang chukyi gyeltsen (1565-1662)",
            "timestamp": "2024-08-27T00:47:25.719120+00:00"
        },
        {
            "path": "nyams len_personal practice/gsol 'debs_prayers of supplication/pan chen blo bzang chos kyi rgyal mtsan_panchen lobsang chukyi gyeltsen (1565-1662)",
            "timestamp": "2024-08-27T00:47:49.099767+00:00"
        }
    ]
}